yamlargs/__init__.py
yamlargs/config.py
yamlargs/lazy.py
yamlargs/parser.py
yamlargs-0.2.1.dist-info/LICENSE
yamlargs-0.2.1.dist-info/METADATA
yamlargs-0.2.1.dist-info/WHEEL
yamlargs-0.2.1.dist-info/top_level.txt
yamlargs-0.2.1.dist-info/RECORD
