Metadata-Version: 2.1
Name: yamlargs
Version: 0.2.1
Summary: YAML based config management for ML
License: UNKNOWN
Platform: UNKNOWN
Requires-Python: >=3
License-File: LICENSE
Requires-Dist: pyyaml
